h4t1c3lib/__init__.py
h4t1c3lib/imports.py
h4t1c3lib/usage_.py
pismikroplib-0.1.0.dist-info/licenses/LICENSE
pismikroplib-0.1.0.dist-info/METADATA
pismikroplib-0.1.0.dist-info/WHEEL
pismikroplib-0.1.0.dist-info/top_level.txt
pismikroplib-0.1.0.dist-info/RECORD
