Metadata-Version: 2.4
Name: pismikroplib
Version: 0.1.0
Summary: Pismikroplar.
Author: h4t1ce
Author-email: H4t1c3 <h4t1c3@pismikrops.com>
License: Creative Commons Legal Code
Requires-Python: >=3.6
License-File: LICENSE
Requires-Dist: requests
Requires-Dist: numpy
Dynamic: author
Dynamic: license-file
Dynamic: requires-python
